Workbook

Sheet 参数
A1: 参数 | B1: 数值
A2: 演示雇主缴费比例 | B2: 0.12
A3: 期初现金 | B3: 50000

Sheet 工资明细
A1: 员工编号 | B1: 部门 | C1: 基本工资 | D1: 出勤比例 | E1: 奖金调整 | F1: 报销 | G1: 扣款 | H1: 应发工资 | I1: 实付员工 | J1: 雇主缴费 | K1: 现金成本
A2: DEMO-001 | B2: 研发 | C2: 10000 | D2: 1 | E2: 1200 | F2: 245.67 | G2: 500 | H2: =ROUND(C2*D2+E2,2) | I2: =ROUND(H2+F2-G2,2) | J2: =ROUND(H2*'参数'!$B$2,2) | K2: =ROUND(H2+F2+J2,2)
A3: DEMO-002 | B3: 销售 | C3: 8000 | D3: 0.5 | E3: 0 | F3: 0 | G3: 320 | H3: =ROUND(C3*D3+E3,2) | I3: =ROUND(H3+F3-G3,2) | J3: =ROUND(H3*'参数'!$B$2,2) | K3: =ROUND(H3+F3+J3,2)
A4: DEMO-003 | B4: 研发 | C4: 6400 | D4: 0.875 | E4: 500 | F4: 88.88 | G4: 400 | H4: =ROUND(C4*D4+E4,2) | I4: =ROUND(H4+F4-G4,2) | J4: =ROUND(H4*'参数'!$B$2,2) | K4: =ROUND(H4+F4+J4,2)
A5: DEMO-004 | B5: 运营 | C5: 7500 | D5: 1 | E5: -100 | F5: 0 | G5: 450 | H5: =ROUND(C5*D5+E5,2) | I5: =ROUND(H5+F5-G5,2) | J5: =ROUND(H5*'参数'!$B$2,2) | K5: =ROUND(H5+F5+J5,2)
A6: 合计 | C6: =SUM(C2:C5) | E6: =SUM(E2:E5) | F6: =SUM(F2:F5) | G6: =SUM(G2:G5) | H6: =SUM(H2:H5) | I6: =SUM(I2:I5) | J6: =SUM(J2:J5) | K6: =SUM(K2:K5)

Sheet 部门汇总
A1: 部门 | B1: 人数 | C1: 应发工资 | D1: 实付员工 | E1: 现金成本
A2: 研发 | B2: =COUNTIF('工资明细'!B2:B5,A2) | C2: =SUMIF('工资明细'!B2:B5,A2,'工资明细'!H2:H5) | D2: =SUMIF('工资明细'!B2:B5,A2,'工资明细'!I2:I5) | E2: =SUMIF('工资明细'!B2:B5,A2,'工资明细'!K2:K5)
A3: 销售 | B3: =COUNTIF('工资明细'!B2:B5,A3) | C3: =SUMIF('工资明细'!B2:B5,A3,'工资明细'!H2:H5) | D3: =SUMIF('工资明细'!B2:B5,A3,'工资明细'!I2:I5) | E3: =SUMIF('工资明细'!B2:B5,A3,'工资明细'!K2:K5)
A4: 运营 | B4: =COUNTIF('工资明细'!B2:B5,A4) | C4: =SUMIF('工资明细'!B2:B5,A4,'工资明细'!H2:H5) | D4: =SUMIF('工资明细'!B2:B5,A4,'工资明细'!I2:I5) | E4: =SUMIF('工资明细'!B2:B5,A4,'工资明细'!K2:K5)
A5: 合计 | B5: =SUM(B2:B4) | C5: =SUM(C2:C4) | D5: =SUM(D2:D4) | E5: =SUM(E2:E4)

Sheet 现金核对
A1: 指标 | B1: 金额
A2: 期初现金 | B2: ='参数'!B3
A3: 现金成本 | B3: ='工资明细'!K6
A4: 期末现金 | B4: =ROUND(B2-B3,2)
A5: 部门成本差额 | B5: =ROUND('部门汇总'!E5-B3,2)
A6: 报销合计 | B6: ='工资明细'!F6
A7: 出勤折算基本工资 | B7: =SUMPRODUCT('工资明细'!C2:C5,'工资明细'!D2:D5)
A8: 员工平均实付 | B8: =AVERAGE('工资明细'!I2:I5)
A9: 最高实付 | B9: =MAX('工资明细'!I2:I5)
A10: 最低实付 | B10: =MIN('工资明细'!I2:I5)
A11: 有奖金员工 | B11: =COUNTIFS('工资明细'!E2:E5,">0",'工资明细'!D2:D5,">=0.8")
A12: 研发报销 | B12: =SUMIFS('工资明细'!F2:F5,'工资明细'!B2:B5,"研发",'工资明细'!F2:F5,">0")
